<?xml version="1.0" encoding="UTF-8"?>
<extension type="package" method="upgrade">
	<name>uk-UA</name>
	<packagename>uk-UA</packagename>
	<version>4.3.2.1</version>
	<creationDate>2023-06-01</creationDate>
	<author>Denys Nosov</author>
	<authorEmail>denys@joomla-ua.org</authorEmail>
	<authorUrl>https://joomla-ua.org</authorUrl>
	<copyright>2006-2023 (C) Joomla! Ukraine (https://joomla-ua.org). All rights reserved.</copyright>
	<license>http://www.gnu.org/licenses/gpl-2.0.html GNU/GPL</license>
	<url>https://joomla-ua.org</url>
	<packager>Joomla! Ukraine</packager>
	<packagerurl>https://joomla-ua.org</packagerurl>
	<description><![CDATA[<h3>Український пакет локалізації Joomla! 4.3.2 (Ukrainian Language Pack)</h3><p>Українська спільнота Joomla!</p><ul><li><a href="https://joomla-ua.org/" target="_blank">Joomla! Україна</a></li><li><a href="https://community.joomla-ua.org/" target="_blank">Форум Joomla! Україна</a></li><li><a href="https://cutt.ly/ZBA8p32" target="_blank">Чат в Telegram</a></li></ul>]]></description>
	<blockChildUninstall>true</blockChildUninstall>
	<files>
		<folder type="language" client="site" id="uk-UA">language/uk-UA</folder>
		<folder type="language" client="administrator" id="uk-UA">administrator/language/uk-UA</folder>
		<folder type="language" client="api" id="uk-UA">api/language/uk-UA</folder>
	</files>
	<updateservers>
		<server type="collection" priority="1" name="Accredited Joomla! Translations">http://update.joomla.org/language/translationlist_4.xml</server>
	</updateservers>
</extension>
